{
    "Company Name": "RBZ Jewellers IPO",
    "IPO_Date": "December 19, 2023 to December 21, 2023",
    "Listing_Date": "Wednesday, December 27, 2023",
    "Face_Value": "10 per share",
    "Price_Band": "95 to 100 per share",
    "Lot_Size": "150 Shares",
    "Total_Issue_Size": "10,000,000 shares (aggregating up to 100.00 Cr)",
    "Fresh_Issue": "10,000,000 shares (aggregating up to 100.00 Cr)",
    "Issue_Type": "Book Built Issue IPO",
    "Listing_At": "BSE, NSE",
    "Share_holding_pre_issue": "30,000,000",
    "Share_holding_post_issue": "40,000,000",
    "Investor_Category": "Maximum Allottees",
    "Anchor_Investor_Shares_Offered": "NA",
    "QIB_Shares_Offered": "NA",
    "NII_(HNI)_Shares_Offered": "",
    "bNII_>_₹10L": "952",
    "sNII_<_₹10L": "476",
    "Retail_Shares_Offered": "23,333",
    "Total_Shares_Offered": "",
    "Bid_Date": "December 18, 2023",
    "Shares_Offered": "2,100,000",
    "Anchor_Portion_Size_(In_Cr.)": "21.00",
    "Anchor_lock-in_period_end_date_for_50%_shares_(30_Days)": "January 21, 2024",
    "Anchor_lock-in_period_end_date_for_remaining_shares_(90_Days)": "March 21, 2024",
    "IPO_Open_Date": "Tuesday, December 19, 2023",
    "IPO_Close_Date": "Thursday, December 21, 2023",
    "Basis_of_Allotment": "Friday, December 22, 2023",
    "Initiation_of_Refunds": "Tuesday, December 26, 2023",
    "Credit_of_Shares_to_Demat": "Tuesday, December 26, 2023",
    "Cut-off_time_for_UPI_mandate_confirmation": "5 PM on December 21, 2023",
    "Application": "Amount",
    "Retail_(Min)": "15,000",
    "Retail_(Max)": "195,000",
    "S-HNI_(Min)": "210,000",
    "S-HNI_(Max)": "990,000",
    "B-HNI_(Min)": "1,005,000",
    "Lot_Size_Calculator": "Lot Size Calculator",
    "Share_Holding_Pre_Issue": "100%",
    "Share_Holding_Post_Issue": "75%",
    "KPI": "Values",
    "ROE": "27.49%",
    "ROCE": "27.49%",
    "Debt/Equity": "1.02",
    "RoNW": "20.08%",
    "": "Post IPO",
    "EPS_(Rs)": "",
    "P/E_(x)": "16.53",
    "Review_By": "Avoid",
    "Brokers": "0",
    "Members": "0"
}