{
    "Company Name": "Vikram Solar IPO",
    "IPO_Date": "August 19, 2025 to August 21, 2025",
    "Listing_Date": "August 26, 2025",
    "Face_Value": "10 per share",
    "Issue_Price_Band": "315 to 332 per share",
    "Issue_Price_Final": "332 per share",
    "Lot_Size": "45 Shares",
    "Sale_Type": "Fresh Capital-cum-Offer for Sale",
    "Total_Issue_Size": "6,26,31,604 shares (aggregating up to 2,079.37 Cr)",
    "Fresh_Issue_": "4,51,80,722 shares (aggregating up to 1,500.00 Cr)",
    "Offer_for_Sale": "1,74,50,882 shares of 10 (aggregating up to 579.37 Cr)",
    "Issue_Type": "Bookbuilding IPO",
    "Listing_At": "BSE, NSE",
    "Share_Holding_Pre_Issue": "31,65,36,309 shares",
    "Share_Holding_Post_Issue": "36,17,17,031 shares",
    "\n\n\nQIB_Shares_Offered": "NA",
    "_Anchor_Investor_Shares_Offered": "NA",
    "_QIB_(Ex._Anchor)_Shares_Offered": "NA",
    "\n\n\nNII_(HNI)_Shares_Offered": "NA",
    "_bNII_>_10L": "9,893",
    "_sNII_<_10L": "4,946",
    "Retail_Shares_Offered": "4,84,792",
    "Employee_Shares_Offered": "NA",
    "Total_Shares_Offered": "",
    "Bid_Date": "August 18, 2025",
    "Shares_Offered": "1,86,99,120",
    "Anchor_Portion_Size_(In_Cr.)": "620.81",
    "Anchor_lock-in_period_end_date_for_50%_shares_(30_Days)": "September 20, 2025",
    "Anchor_lock-in_period_end_date_for_remaining_shares_(90_Days)": "November 19, 2025",
    "IPO_Open_Date": "Tue, Aug 19, 2025",
    "IPO_Close_Date": "Thu, Aug 21, 2025",
    "Tentative_Allotment": "Fri, Aug 22, 2025",
    "Initiation_of_Refunds": "Mon, Aug 25, 2025",
    "Credit_of_Shares_to_Demat": "Mon, Aug 25, 2025",
    "Tentative_Listing_Date": "Tue, Aug 26, 2025",
    "Cut-off_time_for_UPI_mandate_confirmation": "5 PM on Thu, Aug 21, 2025",
    "Retail_(Min)\n": "14,940",
    "Retail_(Max)\n": "1,94,220",
    "S-HNI_(Min)\n": "2,09,160",
    "\nS-HNI_(Max)\n": "9,86,040",
    "\nB-HNI_(Min)\n": "10,00,980",
    "_Promoter_Holding_Pre_Issue": "77.64%",
    "Promoter_Holding_Post_Issue": "63.11%",
    "ROE": "16.57%",
    "ROCE": "24.49%",
    "Debt/Equity": "0.19",
    "RoNW": "11.26%",
    "PAT_Margin": "4.08%",
    "EBITDA_Margin": "14.37%",
    "Price_to_Book_Value": "8.46",
    "EPS_Rs": "3.87",
    "P/E_(x)": "85.88",
    "Brokers": "0",
    "Members": "0"
}